[
  {
    "title": "Life Smile Website",
    "subtitle": "Ecommerce website for Life Smile Company",
    "type": "",
    "description": "",
    "from": "2023-04-23T18:25:43.511Z",
    "to": "2023-04-23T18:25:43.511Z",
    "client": "Life Smile",
    "websiteLink": "https://lifesmile.ae",
    "githubLink": "",
    "androidLink": "",
    "iosLink": "",
    "media": [
      {
        "src": "/images/projects/lifesmile-website/1.png",
        "alt": "Lifesmile website home page | Dergham Portfolio",
        "type": "image"
      }
    ],
    "skills": [
      "Next.js", "React.js", "MySQL", "CSS", "HTML", "Tailwindcss", "AWS", "AWS S3", "Nest.js"
    ]
  },
  {
    "title": "Life Smile Website",
    "subtitle": "Ecommerce website for Life Smile Company",
    "type": "",
    "description": "",
    "from": "2023-04-23T18:25:43.511Z",
    "to": "2023-04-23T18:25:43.511Z",
    "client": "Life Smile",
    "websiteLink": "https://lifesmile.ae",
    "githubLink": "",
    "androidLink": "",
    "iosLink": "",
    "media": [
      {
        "src": "/images/projects/lifesmile-website/1.png",
        "alt": "Lifesmile website home page | Dergham Portfolio",
        "type": "image"
      }
    ],
    "skills": [
      "Next.js", "React.js", "MySQL", "CSS", "HTML", "Tailwindcss", "AWS", "AWS S3", "Nest.js"
    ]
  },
  {
    "title": "Life Smile Website",
    "subtitle": "Ecommerce website for Life Smile Company",
    "type": "",
    "description": "",
    "from": "2023-04-23T18:25:43.511Z",
    "to": "2023-04-23T18:25:43.511Z",
    "client": "Life Smile",
    "websiteLink": "https://lifesmile.ae",
    "githubLink": "",
    "androidLink": "",
    "iosLink": "",
    "media": [
      {
        "src": "/images/projects/lifesmile-website/1.png",
        "alt": "Lifesmile website home page | Dergham Portfolio",
        "type": "image"
      }
    ],
    "skills": [
      "Next.js", "React.js", "MySQL", "CSS", "HTML", "Tailwindcss", "AWS", "AWS S3", "Nest.js"
    ]
  },
  {
    "title": "Life Smile Website",
    "subtitle": "Ecommerce website for Life Smile Company",
    "type": "",
    "description": "",
    "from": "2023-04-23T18:25:43.511Z",
    "to": "2023-04-23T18:25:43.511Z",
    "client": "Life Smile",
    "websiteLink": "https://lifesmile.ae",
    "githubLink": "",
    "androidLink": "",
    "iosLink": "",
    "media": [
      {
        "src": "/images/projects/lifesmile-website/1.png",
        "alt": "Lifesmile website home page | Dergham Portfolio",
        "type": "image"
      }
    ],
    "skills": [
      "Next.js", "React.js", "MySQL", "CSS", "HTML", "Tailwindcss", "AWS", "AWS S3", "Nest.js"
    ]
  },
  {
    "title": "Life Smile Website",
    "subtitle": "Ecommerce website for Life Smile Company",
    "type": "",
    "description": "",
    "from": "2023-04-23T18:25:43.511Z",
    "to": "2023-04-23T18:25:43.511Z",
    "client": "Life Smile",
    "websiteLink": "https://lifesmile.ae",
    "githubLink": "",
    "androidLink": "",
    "iosLink": "",
    "media": [
      {
        "src": "/images/projects/lifesmile-website/1.png",
        "alt": "Lifesmile website home page | Dergham Portfolio",
        "type": "image"
      }
    ],
    "skills": [
      "Next.js", "React.js", "MySQL", "CSS", "HTML", "Tailwindcss", "AWS", "AWS S3", "Nest.js"
    ]
  }
]